flask_bauto/__init__.py
flask_bauto/types.py
flask_bauto/templates/bauto/list.html
flask_bauto-0.1.3.dist-info/licenses/LICENSE
flask_bauto-0.1.3.dist-info/METADATA
flask_bauto-0.1.3.dist-info/WHEEL
flask_bauto-0.1.3.dist-info/top_level.txt
flask_bauto-0.1.3.dist-info/RECORD
