Metadata-Version: 2.4
Name: Flask-Bauto
Version: 0.1.3
License-File: LICENSE
Requires-Dist: Flask-FEFset
Requires-Dist: Flask-UXFab
Requires-Dist: Flask-SQLAlchemy
Requires-Dist: Flask-IAM
Provides-Extra: fullstack
Requires-Dist: Bull-Stack; extra == "fullstack"
Provides-Extra: dev
Requires-Dist: build; extra == "dev"
Requires-Dist: twine; extra == "dev"
Dynamic: license-file
